pytokens/__init__.py
pytokens/__main__.py
pytokens/_mypyc_dummy.py
pytokens/cli.py
pytokens/py.typed
pytokens-0.4.1.dist-info/licenses/LICENSE
pytokens-0.4.1.dist-info/METADATA
pytokens-0.4.1.dist-info/WHEEL
pytokens-0.4.1.dist-info/top_level.txt
pytokens-0.4.1.dist-info/RECORD
